ohdear/__init__.py
ohdear/ohdear.py
ohdear/py.typed
ohdear/types.py
ohdear_sdk-0.3.9.dist-info/METADATA
ohdear_sdk-0.3.9.dist-info/WHEEL
ohdear_sdk-0.3.9.dist-info/licenses/LICENSE.md
ohdear_sdk-0.3.9.dist-info/RECORD
