Metadata-Version: 2.1
Name: ohdear-sdk
Version: 0.3.9
Summary: Oh Dear Python SDK
Project-URL: Source Code, https://github.com/owenvoke/ohdear-python-sdk
Project-URL: Issues, https://github.com/owenvoke/ohdear-python-sdk/issues
Author-email: Owen Voke <development@voke.dev>
License-Expression: MIT
License-File: LICENSE.md
Keywords: ohdear,sdk
Classifier: Intended Audience :: Developers
Classifier: License :: OSI Approved :: MIT License
Classifier: Programming Language :: Python :: 3 :: Only
Requires-Python: >=3.9.0
Requires-Dist: requests>=2.28.1
